<?xml version="1.0" encoding="UTF-8" standalone="yes"?>
<document xmlns="http://www.abbyy.com/FineReader_xml/FineReader10-schema-v1.xml" version="1.0" producer="ABBYY FineReader Engine 11" languages="" xmlns:xsi="http://www.w3.org/2001/XMLSchema-instance" xsi:schemaLocation="http://www.abbyy.com/FineReader_xml/FineReader10-schema-v1.xml http://www.abbyy.com/FineReader_xml/FineReader10-schema-v1.xml">
<page width="2208" height="2960" resolution="600" originalCoords="1">
<block blockType="Text" blockName="">
<text>
<par startIndent="572">
<line baseline="268" l="258" t="126" r="1958" b="294"><formatting lang="EnglishUnitedStates">
<charParams l="258" t="130" r="362" b="270" charConfidence="100">L</charParams>
<charParams l="434" t="130" r="542" b="266" suspicious="1" charConfidence="100">E</charParams>
<charParams l="614" t="130" r="746" b="278" suspicious="1" charConfidence="44">V</charParams>
<charParams l="802" t="130" r="866" b="274" charConfidence="100">I</charParams>
<charParams l="926" t="126" r="1058" b="270" charConfidence="35">A</charParams>
<charParams l="1130" t="126" r="1270" b="270" charConfidence="97">T</charParams>
<charParams l="1334" t="126" r="1474" b="270" suspicious="1" charConfidence="59">H</charParams>
<charParams l="1542" t="130" r="1674" b="270" suspicious="1" charConfidence="27">A</charParams>
<charParams l="1742" t="126" r="1882" b="270" charConfidence="33">N</charParams>
<charParams l="1918" t="238" r="1958" b="294" charConfidence="44">,</charParams></formatting></line></par>
<par align="Center" rightIndent="100">
<line baseline="436" l="933" t="381" r="1249" b="447"><formatting lang="EnglishUnitedStates">
<charParams l="933" t="385" r="985" b="447" suspicious="1" charConfidence="24">s</charParams>
<charParams l="1023" t="385" r="1051" b="437" suspicious="1" charConfidence="23">i</charParams>
<charParams l="1103" t="381" r="1249" b="447" suspicious="1" charConfidence="13">n</charParams></formatting></line></par>
<par align="Center" rightIndent="100">
<line baseline="628" l="341" t="535" r="1875" b="645"><formatting lang="EnglishUnitedStates">
<charParams l="341" t="543" r="427" b="629" charConfidence="97">D</charParams>
<charParams l="435" t="571" r="485" b="631" charConfidence="100">e</charParams>
<charParams l="486" t="543" r="504" b="631"> </charParams>
<charParams l="505" t="543" r="609" b="631" charConfidence="85">M</charParams>
<charParams l="615" t="573" r="661" b="631" charConfidence="32">a</charParams>
<charParams l="665" t="565" r="699" b="629" charConfidence="62">t</charParams>
<charParams l="705" t="569" r="753" b="629" charConfidence="100">e</charParams>
<charParams l="759" t="569" r="797" b="627" charConfidence="33">r</charParams>
<charParams l="801" t="543" r="827" b="627" charConfidence="100">i</charParams>
<charParams l="831" t="571" r="877" b="627" charConfidence="29">a</charParams>
<charParams l="883" t="603" r="909" b="643" charConfidence="100">,</charParams>
<charParams l="910" t="537" r="940" b="643"> </charParams>
<charParams l="941" t="537" r="1001" b="625" charConfidence="15">F</charParams>
<charParams l="1009" t="569" r="1065" b="627" charConfidence="100">o</charParams>
<charParams l="1069" t="569" r="1109" b="627" charConfidence="41">r</charParams>
<charParams l="1109" t="573" r="1201" b="629" charConfidence="100">m</charParams>
<charParams l="1203" t="571" r="1249" b="629" charConfidence="100">a</charParams>
<charParams l="1255" t="603" r="1283" b="645" charConfidence="57">,</charParams>
<charParams l="1284" t="539" r="1304" b="645"> </charParams>
<charParams l="1305" t="539" r="1403" b="627" charConfidence="100">&amp;</charParams>
<charParams l="1404" t="539" r="1422" b="627" suspicious="1"> </charParams>
<charParams l="1423" t="541" r="1489" b="627" suspicious="1" charConfidence="18">P</charParams>
<charParams l="1495" t="567" r="1553" b="629" charConfidence="67">o</charParams>
<charParams l="1557" t="559" r="1593" b="629" charConfidence="73">t</charParams>
<charParams l="1599" t="569" r="1649" b="629" charConfidence="96">e</charParams>
<charParams l="1653" t="535" r="1727" b="629" suspicious="1" charConfidence="67">f</charParams>
<charParams l="1653" t="535" r="1727" b="629" suspicious="1" charConfidence="67">t</charParams>
<charParams l="1733" t="571" r="1779" b="629" charConfidence="100">a</charParams>
<charParams l="1781" t="563" r="1817" b="629" charConfidence="43">t</charParams>
<charParams l="1823" t="571" r="1875" b="629" charConfidence="88">e</charParams></formatting></line></par>
<par align="Center" rightIndent="100">
<line baseline="844" l="447" t="741" r="1763" b="869"><formatting lang="EnglishUnitedStates">
<charParams l="447" t="743" r="547" b="849" charConfidence="68">C</charParams>
<charParams l="548" t="743" r="618" b="849"> </charParams>
<charParams l="619" t="747" r="673" b="849" charConfidence="77">I</charParams>
<charParams l="674" t="743" r="744" b="849"> </charParams>
<charParams l="745" t="743" r="837" b="849" charConfidence="100">V</charParams>
<charParams l="838" t="743" r="916" b="849"> </charParams>
<charParams l="917" t="743" r="969" b="845" charConfidence="78">I</charParams>
<charParams l="970" t="741" r="1042" b="869"> </charParams>
<charParams l="1043" t="741" r="1141" b="869" suspicious="1" charConfidence="25">x</charParams>
<charParams l="1142" t="741" r="1216" b="869"> </charParams>
<charParams l="1217" t="741" r="1311" b="849" charConfidence="32">A</charParams>
<charParams l="1312" t="741" r="1384" b="849"> </charParams>
<charParams l="1385" t="741" r="1483" b="849" charConfidence="63">T</charParams>
<charParams l="1484" t="741" r="1562" b="849"> </charParams>
<charParams l="1563" t="745" r="1615" b="847" charConfidence="91">I</charParams>
<charParams l="1616" t="743" r="1690" b="847"> </charParams>
<charParams l="1691" t="743" r="1763" b="845" charConfidence="53">S</charParams></formatting></line></par>
<par align="Center" rightIndent="100" lineSpacing="1764">
<line baseline="1060" l="291" t="967" r="1929" b="1063"><formatting lang="EnglishUnitedStates">
<charParams l="291" t="971" r="365" b="1057" charConfidence="71">E</charParams>
<charParams l="419" t="969" r="503" b="1061" charConfidence="84">C</charParams>
<charParams l="563" t="969" r="643" b="1061" charConfidence="100">C</charParams>
<charParams l="699" t="975" r="773" b="1059" charConfidence="94">L</charParams>
<charParams l="823" t="975" r="897" b="1059" charConfidence="57">E</charParams>
<charParams l="953" t="967" r="1017" b="1057" charConfidence="65">S</charParams>
<charParams l="1073" t="971" r="1123" b="1055" charConfidence="89">I</charParams>
<charParams l="1181" t="967" r="1261" b="1057" charConfidence="65">A</charParams>
<charParams l="1321" t="969" r="1381" b="1059" charConfidence="100">S</charParams>
<charParams l="1435" t="973" r="1521" b="1061" charConfidence="31">T</charParams>
<charParams l="1575" t="971" r="1625" b="1059" charConfidence="36">I</charParams>
<charParams l="1681" t="967" r="1779" b="1061" charConfidence="32">C</charParams>
<charParams l="1825" t="973" r="1929" b="1063" suspicious="1" charConfidence="-1">S</charParams></formatting></line>
<line baseline="1209" l="635" t="1127" r="1603" b="1209"><formatting lang="EnglishUnitedStates">
<charParams l="635" t="1129" r="699" b="1205" charConfidence="53">E</charParams>
<charParams l="700" t="1129" r="744" b="1205"> </charParams>
<charParams l="745" t="1129" r="819" b="1205" charConfidence="100">T</charParams>
<charParams l="820" t="1129" r="930" b="1207"> </charParams>
<charParams l="931" t="1129" r="1007" b="1207" charConfidence="77">C</charParams>
<charParams l="1008" t="1129" r="1052" b="1207"> </charParams>
<charParams l="1053" t="1129" r="1089" b="1205" charConfidence="60">I</charParams>
<charParams l="1090" t="1129" r="1136" b="1207"> </charParams>
<charParams l="1137" t="1129" r="1207" b="1207" charConfidence="100">V</charParams>
<charParams l="1208" t="1129" r="1250" b="1207"> </charParams>
<charParams l="1251" t="1131" r="1289" b="1203" charConfidence="100">I</charParams>
<charParams l="1290" t="1129" r="1334" b="1205"> </charParams>
<charParams l="1335" t="1129" r="1399" b="1205" charConfidence="100">L</charParams>
<charParams l="1400" t="1129" r="1444" b="1205"> </charParams>
<charParams l="1445" t="1131" r="1483" b="1205" charConfidence="82">I</charParams>
<charParams l="1484" t="1127" r="1528" b="1207"> </charParams>
<charParams l="1529" t="1127" r="1579" b="1207" charConfidence="100">S</charParams>
<charParams l="1585" t="1187" r="1603" b="1209" charConfidence="100">.</charParams></formatting></line></par>
<par align="Center" rightIndent="100">
<line baseline="1364" l="869" t="1318" r="1367" b="1366"><formatting lang="EnglishUnitedStates">
<charParams l="869" t="1319" r="911" b="1363" charConfidence="0">A</charParams>
<charParams l="912" t="1318" r="942" b="1366"> </charParams>
<charParams l="943" t="1318" r="996" b="1366" charConfidence="46">U</charParams>
<charParams l="997" t="1318" r="1025" b="1366"> </charParams>
<charParams l="1026" t="1320" r="1070" b="1363" charConfidence="52">T</charParams>
<charParams l="1071" t="1320" r="1100" b="1363"> </charParams>
<charParams l="1101" t="1320" r="1146" b="1363" charConfidence="33">H</charParams>
<charParams l="1147" t="1319" r="1177" b="1363"> </charParams>
<charParams l="1178" t="1319" r="1224" b="1363" charConfidence="35">O</charParams>
<charParams l="1225" t="1319" r="1254" b="1364"> </charParams>
<charParams l="1255" t="1319" r="1299" b="1364" charConfidence="80">R</charParams>
<charParams l="1300" t="1319" r="1329" b="1364"> </charParams>
<charParams l="1330" t="1319" r="1367" b="1364" charConfidence="64">E</charParams></formatting></line></par>
<par align="Center" rightIndent="100" lineSpacing="1488">
<line baseline="1495" l="436" t="1428" r="1812" b="1512"><formatting lang="EnglishUnitedStates">
<charParams l="436" t="1428" r="500" b="1494" charConfidence="100">T</charParams>
<charParams l="562" t="1431" r="625" b="1495" charConfidence="86">H</charParams>
<charParams l="686" t="1432" r="747" b="1494" charConfidence="81">O</charParams>
<charParams l="810" t="1431" r="880" b="1493" charConfidence="72">M</charParams>
<charParams l="939" t="1432" r="998" b="1492" charConfidence="28">A</charParams>
<charParams l="999" t="1431" r="1138" b="1494"> </charParams>
<charParams l="1139" t="1431" r="1204" b="1494" charConfidence="100">H</charParams>
<charParams l="1267" t="1432" r="1329" b="1492" charConfidence="100">O</charParams>
<charParams l="1395" t="1430" r="1445" b="1494" charConfidence="70">B</charParams>
<charParams l="1505" t="1430" r="1556" b="1498" charConfidence="37">B</charParams>
<charParams l="1620" t="1429" r="1670" b="1494" suspicious="1" charConfidence="33">E</charParams>
<charParams l="1731" t="1434" r="1767" b="1497" suspicious="1" charConfidence="100">S</charParams>
<charParams l="1792" t="1482" r="1812" b="1512" suspicious="1" charConfidence="54">,</charParams></formatting></line>
<line baseline="1617" l="827" t="1553" r="1372" b="1620"><formatting lang="EnglishUnitedStates">
<charParams l="827" t="1557" r="897" b="1618" charConfidence="46">M</charParams>
<charParams l="900" t="1578" r="933" b="1619" charConfidence="36">a</charParams>
<charParams l="936" t="1553" r="954" b="1617" charConfidence="61">l</charParams>
<charParams l="958" t="1576" r="1019" b="1617" suspicious="1" charConfidence="45">m</charParams>
<charParams l="1024" t="1577" r="1057" b="1618" charConfidence="41">e</charParams>
<charParams l="1060" t="1577" r="1084" b="1617" charConfidence="100">s</charParams>
<charParams l="1091" t="1553" r="1129" b="1618" charConfidence="35">b</charParams>
<charParams l="1134" t="1578" r="1173" b="1617" charConfidence="29">u</charParams>
<charParams l="1176" t="1578" r="1201" b="1619" suspicious="1" charConfidence="28">r</charParams>
<charParams l="1203" t="1556" r="1220" b="1617" charConfidence="39">i</charParams>
<charParams l="1227" t="1578" r="1259" b="1619" charConfidence="46">e</charParams>
<charParams l="1264" t="1576" r="1299" b="1617" charConfidence="18">n</charParams>
<charParams l="1308" t="1553" r="1351" b="1620" suspicious="1" charConfidence="42">f</charParams>
<charParams l="1308" t="1553" r="1351" b="1620" suspicious="1" charConfidence="42">i</charParams>
<charParams l="1358" t="1601" r="1372" b="1618" charConfidence="28">.</charParams></formatting></line></par>
</text>
</block>
</page>
</document>